toughguy/__init__.py
toughguy/docker.py
toughguy/guycli.py
toughguy/mysqlfunc.py
toughguy/redisfunc.py
toughguy/toughradius.py
toughguy/toughwlan.py
toughguy/trbfunc.py
toughguy/trshell.py
toughguy/txportal.py
toughguy-0.0.2.dist-info/DESCRIPTION.rst
toughguy-0.0.2.dist-info/eager_resources.txt
toughguy-0.0.2.dist-info/entry_points.txt
toughguy-0.0.2.dist-info/METADATA
toughguy-0.0.2.dist-info/metadata.json
toughguy-0.0.2.dist-info/RECORD
toughguy-0.0.2.dist-info/top_level.txt
toughguy-0.0.2.dist-info/WHEEL
toughguy-0.0.2.dist-info/zip-safe
