Metadata-Version: 2.0
Name: toughguy
Version: 0.0.2
Summary: ToughSTRUCT Software Tools
Home-page: https://github.com/talkincode/toughguy
Author: jamiesun
Author-email: jamiesun.net@gmail.com
License: BSD
Keywords: radius,AAA,authentication,accounting,authorization,toughradius,toughguy
Platform: UNKNOWN
Classifier: Development Status :: 6 - Mature
Classifier: Intended Audience :: Developers
Classifier: Programming Language :: Python :: 2.7
Classifier: Topic :: Software Development :: Libraries :: Python Modules
Classifier: Topic :: System :: Systems Administration :: Authentication/Directory
Requires-Dist: Click
